.env
vams_cli/__init__.py
vams_cli/cli.py
vams_cli-0.2.11.dist-info/entry_points.txt
vams_cli-0.2.11.dist-info/WHEEL
vams_cli-0.2.11.dist-info/METADATA
vams_cli-0.2.11.dist-info/RECORD
